{
 "generated_at": "2026-05-30T22:07:55+00:00",
 "count": 5,
 "markets": [
  {
   "id": "1972137",
   "question": "Will Donald Trump announce that the United States blockade of the Strait of Hormuz has been lifted by May 31, 2026?",
   "slug": "will-donald-trump-announce-that-the-united-states-blockade-of-the-strait-of-hormuz-has-been-lifted-by-may-31-2026-313-388-459-589-533",
   "url": "https://polymarket.com/event/will-donald-trump-announce-that-the-united-states-blockade-of-the-strait-of-hormuz-has-been-lifted-by-may-31-2026-313-388-459-589-533",
   "yes_price": 0.08,
   "volume_24h": 483946.3626550001,
   "volume": 8750794.537193138,
   "end_date": "2026-05-31T00:00:00Z",
   "lat": 26.5667,
   "lng": 56.25,
   "region": "Strait of Hormuz",
   "category": "",
   "yes_price_6h_ago": 0.125,
   "delta_6h": -0.045
  },
  {
   "id": "2169995",
   "question": "MicroStrategy sells any Bitcoin by May 31, 2026?",
   "slug": "microstrategy-sells-any-bitcoin-by-may-31-2026",
   "url": "https://polymarket.com/event/microstrategy-sells-any-bitcoin-by-may-31-2026",
   "yes_price": 0.169,
   "volume_24h": 910803.52194,
   "volume": 7961118.037671913,
   "end_date": "2026-07-01T04:00:00Z",
   "lat": 37.7749,
   "lng": -122.4194,
   "region": "Bitcoin (SF proxy)",
   "category": "",
   "yes_price_6h_ago": 0.125,
   "delta_6h": 0.044
  },
  {
   "id": "2364499",
   "question": "US announces new Iran agreement/ceasefire extension by May 30?",
   "slug": "us-announces-new-iran-agreementceasefire-extension-by-may-30",
   "url": "https://polymarket.com/event/us-announces-new-iran-agreementceasefire-extension-by-may-30",
   "yes_price": 0.0165,
   "volume_24h": 282460.5746909999,
   "volume": 700686.3024719997,
   "end_date": "2026-05-30T00:00:00Z",
   "lat": 32.4279,
   "lng": 53.688,
   "region": "Iran",
   "category": "",
   "yes_price_6h_ago": 0.043,
   "delta_6h": -0.0265
  },
  {
   "id": "2111640",
   "question": "US-Iran nuclear deal by May 31?",
   "slug": "us-iran-nuclear-deal-by-may-31-974",
   "url": "https://polymarket.com/event/us-iran-nuclear-deal-by-may-31-974",
   "yes_price": 0.0305,
   "volume_24h": 456034.4855570001,
   "volume": 6120537.403777908,
   "end_date": "2026-05-31T00:00:00Z",
   "lat": 32.4279,
   "lng": 53.688,
   "region": "Iran",
   "category": "",
   "yes_price_6h_ago": 0.0455,
   "delta_6h": -0.015
  },
  {
   "id": "2340843",
   "question": "US announces new Iran agreement/ceasefire extension by May 31?",
   "slug": "us-announces-new-iran-agreementceasefire-extension-by-may-31-665-831-238",
   "url": "https://polymarket.com/event/us-announces-new-iran-agreementceasefire-extension-by-may-31-665-831-238",
   "yes_price": 0.105,
   "volume_24h": 456249.7442210005,
   "volume": 4523319.705812956,
   "end_date": null,
   "lat": 32.4279,
   "lng": 53.688,
   "region": "Iran",
   "category": "",
   "yes_price_6h_ago": 0.115,
   "delta_6h": -0.01
  }
 ]
}