{
 "generated_at": "2026-06-06T20:16:48+00:00",
 "count": 2,
 "markets": [
  {
   "id": "2270338",
   "question": "US x Iran permanent peace deal by July 31, 2026?",
   "slug": "us-x-iran-permanent-peace-deal-by-july-31-2026-831-252",
   "url": "https://polymarket.com/event/us-x-iran-permanent-peace-deal-by-july-31-2026-831-252",
   "yes_price": 0.295,
   "volume_24h": 504166.2307059958,
   "volume": 5051845.572495105,
   "end_date": "2026-07-31T00:00:00Z",
   "lat": 32.4279,
   "lng": 53.688,
   "region": "Iran",
   "category": "",
   "yes_price_6h_ago": 0.345,
   "delta_6h": -0.05
  },
  {
   "id": "1971905",
   "question": "Strait of Hormuz traffic returns to normal by end of June?",
   "slug": "strait-of-hormuz-traffic-returns-to-normal-by-end-of-june",
   "url": "https://polymarket.com/event/strait-of-hormuz-traffic-returns-to-normal-by-end-of-june",
   "yes_price": 0.145,
   "volume_24h": 221500.828948,
   "volume": 14168593.938118191,
   "end_date": "2026-06-30T00:00:00Z",
   "lat": 26.5667,
   "lng": 56.25,
   "region": "Strait of Hormuz",
   "category": "",
   "yes_price_6h_ago": 0.155,
   "delta_6h": -0.01
  }
 ]
}