{
 "generated_at": "2026-05-11T23:03:40+00:00",
 "count": 50,
 "markets": [
  {
   "id": "2036477",
   "question": "Will Al Ahli Saudi Club win on 2026-05-11?",
   "slug": "spl-taa-ahl-2026-05-11-ahl",
   "url": "https://polymarket.com/event/spl-taa-ahl-2026-05-11-ahl",
   "yes_price": 0.9995,
   "volume_24h": 96295.40372199994,
   "volume": 96359.92840200017,
   "end_date": "2026-05-11T18:00:00Z",
   "lat": 23.8859,
   "lng": 45.0792,
   "region": "Saudi Arabia",
   "category": "",
   "yes_price_6h_ago": 0.475,
   "delta_6h": 0.5245
  },
  {
   "id": "2231250",
   "question": "Will Trump say \"Judge\" or \"Court\" during events with the 2026 National Football Champions?",
   "slug": "will-trump-say-judge-or-court-during-events-with-the-2026-national-football-champions",
   "url": "https://polymarket.com/event/will-trump-say-judge-or-court-during-events-with-the-2026-national-football-champions",
   "yes_price": 0.9995,
   "volume_24h": 668.5818939999998,
   "volume": 668.5818939999999,
   "end_date": "2026-05-11T00:00:00Z",
   "lat": 38.9072,
   "lng": -77.0369,
   "region": "Washington DC",
   "category": "",
   "yes_price_6h_ago": 0.475,
   "delta_6h": 0.5245
  },
  {
   "id": "2218402",
   "question": "Harris vs. Brunclik: Match O/U 21.5",
   "slug": "atp-harris-bruncli-2026-05-11-match-total-21pt5",
   "url": "https://polymarket.com/event/atp-harris-bruncli-2026-05-11-match-total-21pt5",
   "yes_price": 0.9995,
   "volume_24h": 169.657289,
   "volume": 169.657289,
   "end_date": "2026-05-18T09:00:00Z",
   "lat": 38.9072,
   "lng": -77.0369,
   "region": "Washington DC",
   "category": "",
   "yes_price_6h_ago": 0.5,
   "delta_6h": 0.4995
  },
  {
   "id": "2217864",
   "question": "Oeiras 4: Billy Harris vs Petr Brunclik",
   "slug": "atp-harris-bruncli-2026-05-11",
   "url": "https://polymarket.com/event/atp-harris-bruncli-2026-05-11",
   "yes_price": 0.0005,
   "volume_24h": 193549.186203,
   "volume": 199424.82803100103,
   "end_date": "2026-05-18T09:00:00Z",
   "lat": 38.9072,
   "lng": -77.0369,
   "region": "Washington DC",
   "category": "",
   "yes_price_6h_ago": 0.465,
   "delta_6h": -0.4645
  },
  {
   "id": "2038407",
   "question": "Al Taawoun Saudi Club vs. Al Ahli Saudi Club: O/U 2.5",
   "slug": "spl-taa-ahl-2026-05-11-total-2pt5",
   "url": "https://polymarket.com/event/spl-taa-ahl-2026-05-11-total-2pt5",
   "yes_price": 0.9995,
   "volume_24h": 36902.38460399999,
   "volume": 36923.57507599999,
   "end_date": "2026-05-11T18:00:00Z",
   "lat": 23.8859,
   "lng": 45.0792,
   "region": "Saudi Arabia",
   "category": "",
   "yes_price_6h_ago": 0.535,
   "delta_6h": 0.4645
  },
  {
   "id": "2132282",
   "question": "Test Series Bangladesh vs. Pakistan: Bangladesh vs Pakistan - Match goes to Day 5?",
   "slug": "crint-bgd-pak-2026-05-08-match-to-day-5",
   "url": "https://polymarket.com/event/crint-bgd-pak-2026-05-08-match-to-day-5",
   "yes_price": 0.9945,
   "volume_24h": 105.0,
   "volume": 105.0,
   "end_date": "2026-05-15T04:00:00Z",
   "lat": 30.3753,
   "lng": 69.3451,
   "region": "Pakistan",
   "category": "",
   "yes_price_6h_ago": 0.56,
   "delta_6h": 0.4345
  },
  {
   "id": "2038410",
   "question": "Al Taawoun Saudi Club vs. Al Ahli Saudi Club: Both Teams to Score",
   "slug": "spl-taa-ahl-2026-05-11-btts",
   "url": "https://polymarket.com/event/spl-taa-ahl-2026-05-11-btts",
   "yes_price": 0.9995,
   "volume_24h": 7263.795846000001,
   "volume": 7263.795846000001,
   "end_date": "2026-05-11T18:00:00Z",
   "lat": 23.8859,
   "lng": 45.0792,
   "region": "Saudi Arabia",
   "category": "",
   "yes_price_6h_ago": 0.575,
   "delta_6h": 0.4245
  },
  {
   "id": "2168993",
   "question": "Will Quantum Computing (QUBT) beat quarterly earnings?",
   "slug": "qubt-quarterly-earnings-gaap-eps-05-11-2026-neg0pt05",
   "url": "https://polymarket.com/event/qubt-quarterly-earnings-gaap-eps-05-11-2026-neg0pt05",
   "yes_price": 0.9995,
   "volume_24h": 1206.08784,
   "volume": 1212.260671,
   "end_date": "2026-05-11T21:00:00Z",
   "lat": 55.7558,
   "lng": 37.6173,
   "region": "Russia",
   "category": "",
   "yes_price_6h_ago": 0.58,
   "delta_6h": 0.4195
  },
  {
   "id": "2063275",
   "question": "Will Joaquín Panichelli be included in Argentina's official 2026 World Cup squad list?",
   "slug": "will-joaqun-panichelli-be-included-in-argentinas-official-2026-world-cup-squad-list",
   "url": "https://polymarket.com/event/will-joaqun-panichelli-be-included-in-argentinas-official-2026-world-cup-squad-list",
   "yes_price": 0.045,
   "volume_24h": 30.0,
   "volume": 30.0,
   "end_date": "2026-06-02T00:00:00Z",
   "lat": -38.4161,
   "lng": -63.6167,
   "region": "Argentina",
   "category": "",
   "yes_price_6h_ago": 0.42,
   "delta_6h": -0.375
  },
  {
   "id": "2231255",
   "question": "Will Trump say \"World Cup\" during events with the 2026 National Football Champions?",
   "slug": "will-trump-say-world-cup-during-events-with-the-2026-national-football-champions",
   "url": "https://polymarket.com/event/will-trump-say-world-cup-during-events-with-the-2026-national-football-champions",
   "yes_price": 0.0205,
   "volume_24h": 550.203158,
   "volume": 550.203158,
   "end_date": "2026-05-11T00:00:00Z",
   "lat": 38.9072,
   "lng": -77.0369,
   "region": "Washington DC",
   "category": "",
   "yes_price_6h_ago": 0.385,
   "delta_6h": -0.3645
  },
  {
   "id": "2038408",
   "question": "Al Taawoun Saudi Club vs. Al Ahli Saudi Club: O/U 3.5",
   "slug": "spl-taa-ahl-2026-05-11-total-3pt5",
   "url": "https://polymarket.com/event/spl-taa-ahl-2026-05-11-total-3pt5",
   "yes_price": 0.0005,
   "volume_24h": 9456.833082999998,
   "volume": 9456.833082999998,
   "end_date": "2026-05-11T18:00:00Z",
   "lat": 23.8859,
   "lng": 45.0792,
   "region": "Saudi Arabia",
   "category": "",
   "yes_price_6h_ago": 0.325,
   "delta_6h": -0.3245
  },
  {
   "id": "2231254",
   "question": "Will Trump say \"Iran\" during events with the 2026 National Football Champions?",
   "slug": "will-trump-say-iran-during-events-with-the-2026-national-football-champions",
   "url": "https://polymarket.com/event/will-trump-say-iran-during-events-with-the-2026-national-football-champions",
   "yes_price": 0.9995,
   "volume_24h": 488.84340299999997,
   "volume": 488.84340299999997,
   "end_date": "2026-05-11T00:00:00Z",
   "lat": 32.4279,
   "lng": 53.688,
   "region": "Iran",
   "category": "",
   "yes_price_6h_ago": 0.68,
   "delta_6h": 0.3195
  },
  {
   "id": "2126942",
   "question": "Will Starmer say \"Honorable\" during the next Prime Minister's Questions event?",
   "slug": "will-starmer-say-honorable-during-the-next-prime-ministers-questions-event",
   "url": "https://polymarket.com/event/will-starmer-say-honorable-during-the-next-prime-ministers-questions-event",
   "yes_price": 0.39,
   "volume_24h": 330.353526,
   "volume": 588.6274370000001,
   "end_date": "2026-05-06T00:00:00Z",
   "lat": 51.5074,
   "lng": -0.1278,
   "region": "London",
   "category": "",
   "yes_price_6h_ago": 0.69,
   "delta_6h": -0.3
  },
  {
   "id": "2203225",
   "question": "Will South Korea ETF (EWY) hit (HIGH) $197 Week of May 11 2026?",
   "slug": "will-ewy-reach-197-by-may-11-2026",
   "url": "https://polymarket.com/event/will-ewy-reach-197-by-may-11-2026",
   "yes_price": 0.785,
   "volume_24h": 205.064153,
   "volume": 205.064153,
   "end_date": "2026-05-15T20:00:00Z",
   "lat": 35.9078,
   "lng": 127.7669,
   "region": "South Korea",
   "category": "",
   "yes_price_6h_ago": 0.485,
   "delta_6h": 0.3
  },
  {
   "id": "2231258",
   "question": "Will Trump say \"Oval Office\" during events with the 2026 National Football Champions?",
   "slug": "will-trump-say-oval-office-during-events-with-the-2026-national-football-champions",
   "url": "https://polymarket.com/event/will-trump-say-oval-office-during-events-with-the-2026-national-football-champions",
   "yes_price": 0.9995,
   "volume_24h": 377.348273,
   "volume": 377.348273,
   "end_date": "2026-05-11T00:00:00Z",
   "lat": 38.9072,
   "lng": -77.0369,
   "region": "Washington DC",
   "category": "",
   "yes_price_6h_ago": 0.73,
   "delta_6h": 0.2695
  },
  {
   "id": "2036475",
   "question": "Will Al Taawoun Saudi Club win on 2026-05-11?",
   "slug": "spl-taa-ahl-2026-05-11-taa",
   "url": "https://polymarket.com/event/spl-taa-ahl-2026-05-11-taa",
   "yes_price": 0.0005,
   "volume_24h": 17131.139126000002,
   "volume": 17172.80245800001,
   "end_date": "2026-05-11T18:00:00Z",
   "lat": 23.8859,
   "lng": 45.0792,
   "region": "Saudi Arabia",
   "category": "",
   "yes_price_6h_ago": 0.265,
   "delta_6h": -0.2645
  },
  {
   "id": "2036476",
   "question": "Will Al Taawoun Saudi Club vs. Al Ahli Saudi Club end in a draw?",
   "slug": "spl-taa-ahl-2026-05-11-draw",
   "url": "https://polymarket.com/event/spl-taa-ahl-2026-05-11-draw",
   "yes_price": 0.0005,
   "volume_24h": 11047.244342000002,
   "volume": 11113.927652,
   "end_date": "2026-05-11T18:00:00Z",
   "lat": 23.8859,
   "lng": 45.0792,
   "region": "Saudi Arabia",
   "category": "",
   "yes_price_6h_ago": 0.265,
   "delta_6h": -0.2645
  },
  {
   "id": "2213300",
   "question": "Will Trump say \"North Korea\" this week?",
   "slug": "will-trump-say-north-korea-this-week",
   "url": "https://polymarket.com/event/will-trump-say-north-korea-this-week",
   "yes_price": 0.515,
   "volume_24h": 60.592537,
   "volume": 62.59253700000001,
   "end_date": "2026-05-17T00:00:00Z",
   "lat": 40.3399,
   "lng": 127.5101,
   "region": "North Korea",
   "category": "",
   "yes_price_6h_ago": 0.26,
   "delta_6h": 0.255
  },
  {
   "id": "2224819",
   "question": "Bitcoin Up or Down - May 11, 4:00PM-8:00PM ET",
   "slug": "btc-updown-4h-1778529600",
   "url": "https://polymarket.com/event/btc-updown-4h-1778529600",
   "yes_price": 0.245,
   "volume_24h": 14788.012544000001,
   "volume": 14788.012544000016,
   "end_date": "2026-05-12T00:00:00Z",
   "lat": 37.7749,
   "lng": -122.4194,
   "region": "Bitcoin (SF proxy)",
   "category": "",
   "yes_price_6h_ago": 0.495,
   "delta_6h": -0.25
  },
  {
   "id": "2038403",
   "question": "Spread: Al Ahli Saudi Club (-1.5)",
   "slug": "spl-taa-ahl-2026-05-11-spread-away-1pt5",
   "url": "https://polymarket.com/event/spl-taa-ahl-2026-05-11-spread-away-1pt5",
   "yes_price": 0.0005,
   "volume_24h": 2648.9721280000003,
   "volume": 2648.972128000001,
   "end_date": "2026-05-11T18:00:00Z",
   "lat": 23.8859,
   "lng": 45.0792,
   "region": "Saudi Arabia",
   "category": "",
   "yes_price_6h_ago": 0.245,
   "delta_6h": -0.2445
  },
  {
   "id": "2213309",
   "question": "Will Trump say \"Hantavirus\" this week?",
   "slug": "will-trump-say-hantavirus-this-week",
   "url": "https://polymarket.com/event/will-trump-say-hantavirus-this-week",
   "yes_price": 0.525,
   "volume_24h": 947.8412670000001,
   "volume": 1484.2807579999997,
   "end_date": "2026-05-17T00:00:00Z",
   "lat": 38.9072,
   "lng": -77.0369,
   "region": "Washington DC",
   "category": "",
   "yes_price_6h_ago": 0.29,
   "delta_6h": 0.235
  },
  {
   "id": "2099580",
   "question": "Will Keir Starmer be the next leader out before 2027?",
   "slug": "will-keir-starmer-be-the-next-leader-out-before-2027-565",
   "url": "https://polymarket.com/event/will-keir-starmer-be-the-next-leader-out-before-2027-565",
   "yes_price": 0.535,
   "volume_24h": 1522.0186519999997,
   "volume": 3529.4533849999993,
   "end_date": "2026-12-31T00:00:00Z",
   "lat": 51.5074,
   "lng": -0.1278,
   "region": "London",
   "category": "",
   "yes_price_6h_ago": 0.31,
   "delta_6h": 0.225
  },
  {
   "id": "2126915",
   "question": "Will Starmer say \"Mr. Speaker\" 20+ times during the next Prime Minister's Questions event?",
   "slug": "will-starmer-say-mr-speaker-20-times-during-the-next-prime-ministers-questions-event-939",
   "url": "https://polymarket.com/event/will-starmer-say-mr-speaker-20-times-during-the-next-prime-ministers-questions-event-939",
   "yes_price": 0.625,
   "volume_24h": 171.57,
   "volume": 532.9248099999999,
   "end_date": "2026-05-06T00:00:00Z",
   "lat": 51.5074,
   "lng": -0.1278,
   "region": "London",
   "category": "",
   "yes_price_6h_ago": 0.845,
   "delta_6h": -0.22
  },
  {
   "id": "2038406",
   "question": "Al Taawoun Saudi Club vs. Al Ahli Saudi Club: O/U 1.5",
   "slug": "spl-taa-ahl-2026-05-11-total-1pt5",
   "url": "https://polymarket.com/event/spl-taa-ahl-2026-05-11-total-1pt5",
   "yes_price": 0.9995,
   "volume_24h": 7115.222087000001,
   "volume": 7115.222087000002,
   "end_date": "2026-05-11T18:00:00Z",
   "lat": 23.8859,
   "lng": 45.0792,
   "region": "Saudi Arabia",
   "category": "",
   "yes_price_6h_ago": 0.78,
   "delta_6h": 0.2195
  },
  {
   "id": "2063169",
   "question": "Will Ederson be included in Brazil's official 2026 World Cup squad list?",
   "slug": "will-ederson-be-included-in-brazils-official-2026-world-cup-squad-list",
   "url": "https://polymarket.com/event/will-ederson-be-included-in-brazils-official-2026-world-cup-squad-list",
   "yes_price": 0.245,
   "volume_24h": 530.06522,
   "volume": 1751.5577830000002,
   "end_date": "2026-06-02T00:00:00Z",
   "lat": -14.235,
   "lng": -51.9253,
   "region": "Brazil",
   "category": "",
   "yes_price_6h_ago": 0.46,
   "delta_6h": -0.215
  },
  {
   "id": "666598",
   "question": "Will Trump meet with Keir Starmer in 2026?",
   "slug": "will-trump-meet-with-keir-starmer-in-2026",
   "url": "https://polymarket.com/event/will-trump-meet-with-keir-starmer-in-2026",
   "yes_price": 0.4275,
   "volume_24h": 401.980131,
   "volume": 4708.915588000003,
   "end_date": "2026-12-31T00:00:00Z",
   "lat": 38.9072,
   "lng": -77.0369,
   "region": "Washington DC",
   "category": "",
   "yes_price_6h_ago": 0.6285,
   "delta_6h": -0.201
  },
  {
   "id": "2045606",
   "question": "Will Thien Ho advance from the CA-06 primary election?",
   "slug": "will-thien-ho-advance-from-the-ca-06-primary-election",
   "url": "https://polymarket.com/event/will-thien-ho-advance-from-the-ca-06-primary-election",
   "yes_price": 0.115,
   "volume_24h": 365.670768,
   "volume": 901.6707680000001,
   "end_date": "2026-06-02T00:00:00Z",
   "lat": 38.9072,
   "lng": -77.0369,
   "region": "US Election",
   "category": "",
   "yes_price_6h_ago": 0.31,
   "delta_6h": -0.195
  },
  {
   "id": "2203237",
   "question": "Will South Korea ETF (EWY) hit (LOW) $185 Week of May 11 2026?",
   "slug": "will-ewy-dip-to-185-by-may-11-2026",
   "url": "https://polymarket.com/event/will-ewy-dip-to-185-by-may-11-2026",
   "yes_price": 0.31,
   "volume_24h": 310.0,
   "volume": 310.0,
   "end_date": "2026-05-15T20:00:00Z",
   "lat": 35.9078,
   "lng": 127.7669,
   "region": "South Korea",
   "category": "",
   "yes_price_6h_ago": 0.5,
   "delta_6h": -0.19
  },
  {
   "id": "2126920",
   "question": "Will Starmer say \"NHS\" during the next Prime Minister's Questions event?",
   "slug": "will-starmer-say-nhs-during-the-next-prime-ministers-questions-event-693",
   "url": "https://polymarket.com/event/will-starmer-say-nhs-during-the-next-prime-ministers-questions-event-693",
   "yes_price": 0.605,
   "volume_24h": 151.585819,
   "volume": 629.3701130000001,
   "end_date": "2026-05-06T00:00:00Z",
   "lat": 51.5074,
   "lng": -0.1278,
   "region": "London",
   "category": "",
   "yes_price_6h_ago": 0.42,
   "delta_6h": 0.185
  },
  {
   "id": "1835812",
   "question": "Will Reina Ueda as Reze (Chainsaw Man – The Movie: Reze Arc) win Best Anime Voice Artist Performance (Japanese) at the 2026 Crunchyroll Anime Awards?",
   "slug": "will-reina-ueda-as-reze-chainsaw-man-the-movie-reze-arc-win-best-anime-voice-artist-performance-japanese-at-the-2026-crunchyroll-anime-awards",
   "url": "https://polymarket.com/event/will-reina-ueda-as-reze-chainsaw-man-the-movie-reze-arc-win-best-anime-voice-artist-performance-japanese-at-the-2026-crunchyroll-anime-awards",
   "yes_price": 0.298,
   "volume_24h": 76.814083,
   "volume": 2526.762945000001,
   "end_date": "2026-05-23T00:00:00Z",
   "lat": 36.2048,
   "lng": 138.2529,
   "region": "Japan",
   "category": "",
   "yes_price_6h_ago": 0.48,
   "delta_6h": -0.182
  },
  {
   "id": "2120741",
   "question": "Will voter turnout be between 90% and 95% in the 2026 Maltese general election?",
   "slug": "will-voter-turnout-be-between-90-and-95-in-the-2026-maltese-general-election",
   "url": "https://polymarket.com/event/will-voter-turnout-be-between-90-and-95-in-the-2026-maltese-general-election",
   "yes_price": 0.09,
   "volume_24h": 747.493894,
   "volume": 5726.540664,
   "end_date": "2026-05-30T00:00:00Z",
   "lat": 38.9072,
   "lng": -77.0369,
   "region": "US Election",
   "category": "",
   "yes_price_6h_ago": 0.2715,
   "delta_6h": -0.1815
  },
  {
   "id": "2126922",
   "question": "Will Starmer say \"Apologize\" or \"Apology\" during the next Prime Minister's Questions event?",
   "slug": "will-starmer-say-apologize-or-apology-during-the-next-prime-ministers-questions-event",
   "url": "https://polymarket.com/event/will-starmer-say-apologize-or-apology-during-the-next-prime-ministers-questions-event",
   "yes_price": 0.445,
   "volume_24h": 19.085073,
   "volume": 281.86882799999995,
   "end_date": "2026-05-06T00:00:00Z",
   "lat": 51.5074,
   "lng": -0.1278,
   "region": "London",
   "category": "",
   "yes_price_6h_ago": 0.265,
   "delta_6h": 0.18
  },
  {
   "id": "2231249",
   "question": "Will Trump say \"Transgender\" during events with the 2026 National Football Champions?",
   "slug": "will-trump-say-transgender-during-events-with-the-2026-national-football-champions",
   "url": "https://polymarket.com/event/will-trump-say-transgender-during-events-with-the-2026-national-football-champions",
   "yes_price": 0.0255,
   "volume_24h": 479.410622,
   "volume": 479.4106219999999,
   "end_date": "2026-05-11T00:00:00Z",
   "lat": 38.9072,
   "lng": -77.0369,
   "region": "Washington DC",
   "category": "",
   "yes_price_6h_ago": 0.205,
   "delta_6h": -0.1795
  },
  {
   "id": "2120739",
   "question": "Will voter turnout be less than 85% in the 2026 Maltese general election?",
   "slug": "will-voter-turnout-be-less-than-85-in-the-2026-maltese-general-election",
   "url": "https://polymarket.com/event/will-voter-turnout-be-less-than-85-in-the-2026-maltese-general-election",
   "yes_price": 0.635,
   "volume_24h": 441.730623,
   "volume": 6904.940835000001,
   "end_date": "2026-05-30T00:00:00Z",
   "lat": 38.9072,
   "lng": -77.0369,
   "region": "US Election",
   "category": "",
   "yes_price_6h_ago": 0.465,
   "delta_6h": 0.17
  },
  {
   "id": "701702",
   "question": "Labour leadership election scheduled by June 30?",
   "slug": "labour-leadership-election-scheduled-by-june-30",
   "url": "https://polymarket.com/event/labour-leadership-election-scheduled-by-june-30",
   "yes_price": 0.8,
   "volume_24h": 606.469861,
   "volume": 19863.558804999982,
   "end_date": "2026-06-30T00:00:00Z",
   "lat": 38.9072,
   "lng": -77.0369,
   "region": "US Election",
   "category": "",
   "yes_price_6h_ago": 0.635,
   "delta_6h": 0.165
  },
  {
   "id": "2232280",
   "question": "Will Russia capture all of Huliaipole by June 30?",
   "slug": "will-russia-capture-all-of-huliaipole-by-june-30",
   "url": "https://polymarket.com/event/will-russia-capture-all-of-huliaipole-by-june-30",
   "yes_price": 0.285,
   "volume_24h": 191.044599,
   "volume": 191.044599,
   "end_date": "2026-06-30T00:00:00Z",
   "lat": 61.524,
   "lng": 105.3188,
   "region": "Russia",
   "category": "",
   "yes_price_6h_ago": 0.445,
   "delta_6h": -0.16
  },
  {
   "id": "665264",
   "question": "Will Donald Trump visit Japan in 2026?",
   "slug": "will-donald-trump-visit-japan-in-2026",
   "url": "https://polymarket.com/event/will-donald-trump-visit-japan-in-2026",
   "yes_price": 0.67,
   "volume_24h": 873.423477,
   "volume": 6134.684684000003,
   "end_date": "2026-12-31T00:00:00Z",
   "lat": 36.2048,
   "lng": 138.2529,
   "region": "Japan",
   "category": "",
   "yes_price_6h_ago": 0.825,
   "delta_6h": -0.155
  },
  {
   "id": "2126930",
   "question": "Will Starmer say \"Investment\" during the next Prime Minister's Questions event?",
   "slug": "will-starmer-say-investment-during-the-next-prime-ministers-questions-event",
   "url": "https://polymarket.com/event/will-starmer-say-investment-during-the-next-prime-ministers-questions-event",
   "yes_price": 0.485,
   "volume_24h": 224.87,
   "volume": 750.762769,
   "end_date": "2026-05-06T00:00:00Z",
   "lat": 51.5074,
   "lng": -0.1278,
   "region": "London",
   "category": "",
   "yes_price_6h_ago": 0.64,
   "delta_6h": -0.155
  },
  {
   "id": "2038409",
   "question": "Al Taawoun Saudi Club vs. Al Ahli Saudi Club: O/U 4.5",
   "slug": "spl-taa-ahl-2026-05-11-total-4pt5",
   "url": "https://polymarket.com/event/spl-taa-ahl-2026-05-11-total-4pt5",
   "yes_price": 0.0005,
   "volume_24h": 2791.528977,
   "volume": 2791.5289769999995,
   "end_date": "2026-05-11T18:00:00Z",
   "lat": 23.8859,
   "lng": 45.0792,
   "region": "Saudi Arabia",
   "category": "",
   "yes_price_6h_ago": 0.155,
   "delta_6h": -0.1545
  },
  {
   "id": "2227270",
   "question": "Will Ethereum dip to $2,300 on May 11?",
   "slug": "will-ethereum-dip-to-2300-on-may-11",
   "url": "https://polymarket.com/event/will-ethereum-dip-to-2300-on-may-11",
   "yes_price": 0.04,
   "volume_24h": 5062.145164000001,
   "volume": 5062.145163999992,
   "end_date": "2026-05-12T04:00:00Z",
   "lat": 40.7128,
   "lng": -74.006,
   "region": "Ethereum (NYC proxy)",
   "category": "",
   "yes_price_6h_ago": 0.185,
   "delta_6h": -0.145
  },
  {
   "id": "2116397",
   "question": "Will USD fall to 1.7M Iranian rials by May 31?",
   "slug": "will-usd-fall-to-1pt7m-iranian-rials-by-may-31",
   "url": "https://polymarket.com/event/will-usd-fall-to-1pt7m-iranian-rials-by-may-31",
   "yes_price": 0.325,
   "volume_24h": 1224.242743,
   "volume": 10324.361870000002,
   "end_date": "2026-05-31T00:00:00Z",
   "lat": 32.4279,
   "lng": 53.688,
   "region": "Iran",
   "category": "",
   "yes_price_6h_ago": 0.18,
   "delta_6h": 0.145
  },
  {
   "id": "2231205",
   "question": "Starmer out by May 31, 2026?",
   "slug": "starmer-out-by-may-31-2026",
   "url": "https://polymarket.com/event/starmer-out-by-may-31-2026",
   "yes_price": 0.575,
   "volume_24h": 99775.22875800001,
   "volume": 99775.22875800004,
   "end_date": "2026-06-30T12:00:00Z",
   "lat": 51.5074,
   "lng": -0.1278,
   "region": "London",
   "category": "",
   "yes_price_6h_ago": 0.435,
   "delta_6h": 0.14
  },
  {
   "id": "2169752",
   "question": "Will Trump announce a Taiwan arms sales halt?",
   "slug": "will-trump-announce-a-taiwan-arms-sales-halt",
   "url": "https://polymarket.com/event/will-trump-announce-a-taiwan-arms-sales-halt",
   "yes_price": 0.055,
   "volume_24h": 267.609473,
   "volume": 267.60947300000004,
   "end_date": "2026-05-22T00:00:00Z",
   "lat": 23.6978,
   "lng": 120.9605,
   "region": "Taiwan",
   "category": "",
   "yes_price_6h_ago": 0.195,
   "delta_6h": -0.14
  },
  {
   "id": "2125371",
   "question": "Will Donald Trump publicly insult Friedrich Merz by May 31, 2026?",
   "slug": "will-donald-trump-publicly-insult-friedrich-merz-by-may-31-2026",
   "url": "https://polymarket.com/event/will-donald-trump-publicly-insult-friedrich-merz-by-may-31-2026",
   "yes_price": 0.295,
   "volume_24h": 63.723872,
   "volume": 838.2531449999999,
   "end_date": "2026-05-31T00:00:00Z",
   "lat": 38.9072,
   "lng": -77.0369,
   "region": "Washington DC",
   "category": "",
   "yes_price_6h_ago": 0.43,
   "delta_6h": -0.135
  },
  {
   "id": "2126914",
   "question": "Will Starmer say \"Mr. Speaker\" 10+ times during the next Prime Minister's Questions event?",
   "slug": "will-starmer-say-mr-speaker-10-times-during-the-next-prime-ministers-questions-event-525",
   "url": "https://polymarket.com/event/will-starmer-say-mr-speaker-10-times-during-the-next-prime-ministers-questions-event-525",
   "yes_price": 0.7995,
   "volume_24h": 2345.1824069999993,
   "volume": 14281.636667000006,
   "end_date": "2026-05-06T00:00:00Z",
   "lat": 51.5074,
   "lng": -0.1278,
   "region": "London",
   "category": "",
   "yes_price_6h_ago": 0.932,
   "delta_6h": -0.1325
  },
  {
   "id": "2231573",
   "question": "Will the price of Bitcoin be above $84,000 on May 18?",
   "slug": "bitcoin-above-84k-on-may-18",
   "url": "https://polymarket.com/event/bitcoin-above-84k-on-may-18",
   "yes_price": 0.275,
   "volume_24h": 111.671656,
   "volume": 111.67165600000001,
   "end_date": "2026-05-18T16:00:00Z",
   "lat": 37.7749,
   "lng": -122.4194,
   "region": "Bitcoin (SF proxy)",
   "category": "",
   "yes_price_6h_ago": 0.145,
   "delta_6h": 0.13
  },
  {
   "id": "2213302",
   "question": "Will Trump say \"Transgender\" this week?",
   "slug": "will-trump-say-transgender-this-week-523",
   "url": "https://polymarket.com/event/will-trump-say-transgender-this-week-523",
   "yes_price": 0.625,
   "volume_24h": 513.0071109999999,
   "volume": 1660.3976450000002,
   "end_date": "2026-05-17T00:00:00Z",
   "lat": 38.9072,
   "lng": -77.0369,
   "region": "Washington DC",
   "category": "",
   "yes_price_6h_ago": 0.75,
   "delta_6h": -0.125
  },
  {
   "id": "1366573",
   "question": "Will Partido da Social Democracia Brasileira (PSDB) hold the most seats as a result of the next Brazilian Senate election?",
   "slug": "will-partido-da-social-democracia-brasileira-psdb-hold-the-most-seats-as-a-result-of-the-next-brazilian-senate-election",
   "url": "https://polymarket.com/event/will-partido-da-social-democracia-brasileira-psdb-hold-the-most-seats-as-a-result-of-the-next-brazilian-senate-election",
   "yes_price": 0.041,
   "volume_24h": 33.18,
   "volume": 779.13,
   "end_date": "2026-10-04T00:00:00Z",
   "lat": 38.9072,
   "lng": -77.0369,
   "region": "US Election",
   "category": "",
   "yes_price_6h_ago": 0.165,
   "delta_6h": -0.124
  },
  {
   "id": "1439549",
   "question": "Fed rate cut by September 2026 meeting?",
   "slug": "fed-rate-cut-by-september-2026-meeting-264-382",
   "url": "https://polymarket.com/event/fed-rate-cut-by-september-2026-meeting-264-382",
   "yes_price": 0.1065,
   "volume_24h": 398.875277,
   "volume": 91938.2016919999,
   "end_date": "2026-06-17T00:00:00Z",
   "lat": 38.9072,
   "lng": -77.0369,
   "region": "Federal Reserve",
   "category": "",
   "yes_price_6h_ago": 0.221,
   "delta_6h": -0.1145
  },
  {
   "id": "2136922",
   "question": "Will Zelenskyy post 80-99 posts from May 5 to May 12, 2026?",
   "slug": "zelenskyy-of-tweets-may-5-may-12-2026-80-99",
   "url": "https://polymarket.com/event/zelenskyy-of-tweets-may-5-may-12-2026-80-99",
   "yes_price": 0.715,
   "volume_24h": 334.002812,
   "volume": 604.62699,
   "end_date": "2026-05-12T16:00:00Z",
   "lat": 50.4501,
   "lng": 30.5234,
   "region": "Ukraine",
   "category": "",
   "yes_price_6h_ago": 0.605,
   "delta_6h": 0.11
  }
 ]
}