{
 "generated_at": "2026-06-11T00:24:08+00:00",
 "count": 11,
 "markets": [
  {
   "id": "2296152",
   "question": "Israel closes its airspace by June 15?",
   "slug": "israel-closes-its-airspace-by-june-15-687-594-783-732-455-613-653",
   "url": "https://polymarket.com/event/israel-closes-its-airspace-by-june-15-687-594-783-732-455-613-653",
   "yes_price": 0.195,
   "volume_24h": 268809.29983899964,
   "volume": 4363536.931350969,
   "end_date": "2026-06-15T00:00:00Z",
   "lat": 31.0461,
   "lng": 34.8516,
   "region": "Israel",
   "category": "",
   "yes_price_6h_ago": 0.255,
   "delta_6h": -0.06
  },
  {
   "id": "2466413",
   "question": "Israel closes its airspace by June 10?",
   "slug": "israel-closes-its-airspace-by-june-10",
   "url": "https://polymarket.com/event/israel-closes-its-airspace-by-june-10",
   "yes_price": 0.011,
   "volume_24h": 711622.6038579999,
   "volume": 900496.3509929996,
   "end_date": "2026-06-10T00:00:00Z",
   "lat": 31.0461,
   "lng": 34.8516,
   "region": "Israel",
   "category": "",
   "yes_price_6h_ago": 0.043,
   "delta_6h": -0.032
  },
  {
   "id": "2354003",
   "question": "US announces new Iran agreement/ceasefire extension by June 30?",
   "slug": "us-announces-new-iran-agreementceasefire-extension-by-june-30-848-925-757-129-337",
   "url": "https://polymarket.com/event/us-announces-new-iran-agreementceasefire-extension-by-june-30-848-925-757-129-337",
   "yes_price": 0.345,
   "volume_24h": 251461.25013600008,
   "volume": 2100858.57987201,
   "end_date": "2026-06-30T00:00:00Z",
   "lat": 32.4279,
   "lng": 53.688,
   "region": "Iran",
   "category": "",
   "yes_price_6h_ago": 0.375,
   "delta_6h": -0.03
  },
  {
   "id": "1971905",
   "question": "Strait of Hormuz traffic returns to normal by end of June?",
   "slug": "strait-of-hormuz-traffic-returns-to-normal-by-end-of-june",
   "url": "https://polymarket.com/event/strait-of-hormuz-traffic-returns-to-normal-by-end-of-june",
   "yes_price": 0.075,
   "volume_24h": 767329.3472779999,
   "volume": 16736654.390057247,
   "end_date": "2026-06-30T00:00:00Z",
   "lat": 26.5667,
   "lng": 56.25,
   "region": "Strait of Hormuz",
   "category": "",
   "yes_price_6h_ago": 0.095,
   "delta_6h": -0.02
  },
  {
   "id": "2420774",
   "question": "US announces new Iran agreement/ceasefire extension by June 15?",
   "slug": "us-announces-new-iran-agreementceasefire-extension-by-june-15-2889",
   "url": "https://polymarket.com/event/us-announces-new-iran-agreementceasefire-extension-by-june-15-2889",
   "yes_price": 0.155,
   "volume_24h": 246871.09268200002,
   "volume": 616695.1242620024,
   "end_date": "2026-05-29T00:00:00Z",
   "lat": 32.4279,
   "lng": 53.688,
   "region": "Iran",
   "category": "",
   "yes_price_6h_ago": 0.135,
   "delta_6h": 0.02
  },
  {
   "id": "1962237",
   "question": "US x Iran permanent peace deal by June 30, 2026?",
   "slug": "us-x-iran-permanent-peace-deal-by-june-30-2026-837-641-896-877-363-892-537-597",
   "url": "https://polymarket.com/event/us-x-iran-permanent-peace-deal-by-june-30-2026-837-641-896-877-363-892-537-597",
   "yes_price": 0.165,
   "volume_24h": 1186989.5583529999,
   "volume": 22754764.48686949,
   "end_date": "2026-05-31T00:00:00Z",
   "lat": 32.4279,
   "lng": 53.688,
   "region": "Iran",
   "category": "",
   "yes_price_6h_ago": 0.15,
   "delta_6h": 0.015
  },
  {
   "id": "2475213",
   "question": "Trump announces US x Iran ceasefire over by June 15?",
   "slug": "trump-announces-us-x-iran-ceasefire-over-by-june-15-20260607232556275-193",
   "url": "https://polymarket.com/event/trump-announces-us-x-iran-ceasefire-over-by-june-15-20260607232556275-193",
   "yes_price": 0.185,
   "volume_24h": 313411.18353199994,
   "volume": 454875.54879200045,
   "end_date": "2026-06-16T03:59:00Z",
   "lat": 32.4279,
   "lng": 53.688,
   "region": "Iran",
   "category": "",
   "yes_price_6h_ago": 0.17,
   "delta_6h": 0.015
  },
  {
   "id": "947269",
   "question": "Will Keiko Fujimori win the 2026 Peruvian presidential election?",
   "slug": "will-keiko-fujimori-win-the-2026-peruvian-presidential-election",
   "url": "https://polymarket.com/event/will-keiko-fujimori-win-the-2026-peruvian-presidential-election",
   "yes_price": 0.932,
   "volume_24h": 1260956.8544050003,
   "volume": 18994325.096457962,
   "end_date": "2026-06-07T00:00:00Z",
   "lat": 38.9072,
   "lng": -77.0369,
   "region": "US Election",
   "category": "",
   "yes_price_6h_ago": 0.946,
   "delta_6h": -0.014
  },
  {
   "id": "947289",
   "question": "Will Roberto Sánchez Palomino win the 2026 Peruvian presidential election?",
   "slug": "will-roberto-snchez-palomino-win-the-2026-peruvian-presidential-election",
   "url": "https://polymarket.com/event/will-roberto-snchez-palomino-win-the-2026-peruvian-presidential-election",
   "yes_price": 0.0655,
   "volume_24h": 3497327.894616011,
   "volume": 29701352.55152321,
   "end_date": "2026-06-07T00:00:00Z",
   "lat": 38.9072,
   "lng": -77.0369,
   "region": "US Election",
   "category": "",
   "yes_price_6h_ago": 0.054,
   "delta_6h": 0.0115
  },
  {
   "id": "2326841",
   "question": "Spread: Mexico (-1.5)",
   "slug": "fifwc-mex-rsa-2026-06-11-spread-home-1pt5",
   "url": "https://polymarket.com/event/fifwc-mex-rsa-2026-06-11-spread-home-1pt5",
   "yes_price": 0.395,
   "volume_24h": 492510.7097810002,
   "volume": 529894.5581149992,
   "end_date": "2026-06-11T19:00:00Z",
   "lat": 23.6345,
   "lng": -102.5528,
   "region": "Mexico",
   "category": "",
   "yes_price_6h_ago": 0.405,
   "delta_6h": -0.01
  },
  {
   "id": "2176262",
   "question": "Strait of Hormuz traffic returns to normal by July 31?",
   "slug": "strait-of-hormuz-traffic-returns-to-normal-by-july-31",
   "url": "https://polymarket.com/event/strait-of-hormuz-traffic-returns-to-normal-by-july-31",
   "yes_price": 0.255,
   "volume_24h": 235893.63234900008,
   "volume": 3576957.034125958,
   "end_date": "2026-07-31T00:00:00Z",
   "lat": 26.5667,
   "lng": 56.25,
   "region": "Strait of Hormuz",
   "category": "",
   "yes_price_6h_ago": 0.265,
   "delta_6h": -0.01
  }
 ]
}