{
 "generated_at": "2026-06-30T21:01:08+00:00",
 "count": 29,
 "markets": [
  {
   "id": "2063133",
   "question": "Will Shimelis Abdisa be the next Prime Minister of Ethiopia?",
   "slug": "will-shimelis-abdisa-be-the-next-prime-minister-of-ethiopia",
   "url": "https://polymarket.com/event/will-shimelis-abdisa-be-the-next-prime-minister-of-ethiopia",
   "yes_price": 0.0025,
   "volume_24h": 6044112.131,
   "volume": 19120126.177465,
   "end_date": "2026-06-01T00:00:00Z",
   "lat": 9.145,
   "lng": 40.4897,
   "region": "Ethiopia",
   "category": ""
  },
  {
   "id": "558945",
   "question": "Will Mexico win the 2026 FIFA World Cup?",
   "slug": "will-mexico-win-the-2026-fifa-world-cup-529",
   "url": "https://polymarket.com/event/will-mexico-win-the-2026-fifa-world-cup-529",
   "yes_price": 0.0195,
   "volume_24h": 5919323.607381991,
   "volume": 108124060.81065264,
   "end_date": "2026-07-20T00:00:00Z",
   "lat": 23.6345,
   "lng": -102.5528,
   "region": "Mexico",
   "category": ""
  },
  {
   "id": "2063135",
   "question": "Will Gedion Timothewos be the next Prime Minister of Ethiopia?",
   "slug": "will-gedion-timothewos-be-the-next-prime-minister-of-ethiopia",
   "url": "https://polymarket.com/event/will-gedion-timothewos-be-the-next-prime-minister-of-ethiopia",
   "yes_price": 0.0025,
   "volume_24h": 5092326.650399,
   "volume": 27345440.430097993,
   "end_date": "2026-06-01T00:00:00Z",
   "lat": 9.145,
   "lng": 40.4897,
   "region": "Ethiopia",
   "category": ""
  },
  {
   "id": "558938",
   "question": "Will Argentina win the 2026 FIFA World Cup?",
   "slug": "will-argentina-win-the-2026-fifa-world-cup-245",
   "url": "https://polymarket.com/event/will-argentina-win-the-2026-fifa-world-cup-245",
   "yes_price": 0.1935,
   "volume_24h": 2651502.3366429913,
   "volume": 86385943.39655551,
   "end_date": "2026-07-20T00:00:00Z",
   "lat": -38.4161,
   "lng": -63.6167,
   "region": "Argentina",
   "category": ""
  },
  {
   "id": "558937",
   "question": "Will Brazil win the 2026 FIFA World Cup?",
   "slug": "will-brazil-win-the-2026-fifa-world-cup-183",
   "url": "https://polymarket.com/event/will-brazil-win-the-2026-fifa-world-cup-183",
   "yes_price": 0.0705,
   "volume_24h": 2019913.7381190022,
   "volume": 69133938.24341899,
   "end_date": "2026-07-20T00:00:00Z",
   "lat": -14.235,
   "lng": -51.9253,
   "region": "Brazil",
   "category": ""
  },
  {
   "id": "2718892",
   "question": "Will Mexico win on 2026-06-30?",
   "slug": "fifwc-mex-ecu-2026-06-30-mex",
   "url": "https://polymarket.com/event/fifwc-mex-ecu-2026-06-30-mex",
   "yes_price": 0.435,
   "volume_24h": 1566679.0938779977,
   "volume": 2123085.847040045,
   "end_date": "2026-07-01T01:00:00Z",
   "lat": 23.6345,
   "lng": -102.5528,
   "region": "Mexico",
   "category": ""
  },
  {
   "id": "560317",
   "question": "Putin out as President of Russia by December 31, 2026?",
   "slug": "putin-out-before-2027",
   "url": "https://polymarket.com/event/putin-out-before-2027",
   "yes_price": 0.135,
   "volume_24h": 897431.4614479995,
   "volume": 11996512.040462054,
   "end_date": "2026-12-31T18:30:00Z",
   "lat": 55.7558,
   "lng": 37.6173,
   "region": "Russia",
   "category": ""
  },
  {
   "id": "1971905",
   "question": "Strait of Hormuz traffic returns to normal by end of June?",
   "slug": "strait-of-hormuz-traffic-returns-to-normal-by-end-of-june",
   "url": "https://polymarket.com/event/strait-of-hormuz-traffic-returns-to-normal-by-end-of-june",
   "yes_price": 0.0045,
   "volume_24h": 705565.3603499996,
   "volume": 40086837.01982219,
   "end_date": "2026-06-30T00:00:00Z",
   "lat": 26.5667,
   "lng": 56.25,
   "region": "Strait of Hormuz",
   "category": ""
  },
  {
   "id": "2410575",
   "question": "Will Bitcoin dip to $57,500 in June?",
   "slug": "will-bitcoin-dip-to-57pt5k-in-june-2026-623-575",
   "url": "https://polymarket.com/event/will-bitcoin-dip-to-57pt5k-in-june-2026-623-575",
   "yes_price": 0.0945,
   "volume_24h": 671970.5179519999,
   "volume": 4641334.499102002,
   "end_date": "2026-07-01T04:00:00Z",
   "lat": 37.7749,
   "lng": -122.4194,
   "region": "Bitcoin (SF proxy)",
   "category": ""
  },
  {
   "id": "2475212",
   "question": "Trump announces US x Iran ceasefire over by June 30?",
   "slug": "trump-announces-us-x-iran-ceasefire-over-by-june-30-20260607232556276-219",
   "url": "https://polymarket.com/event/trump-announces-us-x-iran-ceasefire-over-by-june-30-20260607232556276-219",
   "yes_price": 0.0015,
   "volume_24h": 628029.312759,
   "volume": 2235599.896645997,
   "end_date": "2026-07-01T03:59:00Z",
   "lat": 32.4279,
   "lng": 53.688,
   "region": "Iran",
   "category": ""
  },
  {
   "id": "682721",
   "question": "Will Amir Ohana be the next Prime Minister of Israel?",
   "slug": "will-amir-ohana-be-the-next-prime-minister-of-israel",
   "url": "https://polymarket.com/event/will-amir-ohana-be-the-next-prime-minister-of-israel",
   "yes_price": 0.0035,
   "volume_24h": 527476.111416,
   "volume": 1622804.2935829954,
   "end_date": "2026-12-31T00:00:00Z",
   "lat": 31.0461,
   "lng": 34.8516,
   "region": "Israel",
   "category": ""
  },
  {
   "id": "2646932",
   "question": "Will the next diplomatic US-Iran meeting be in another country by September 30, 2026?",
   "slug": "will-the-next-diplomatic-us-iran-meeting-be-in-another-country-by-september-30-2026-20260622185050781",
   "url": "https://polymarket.com/event/will-the-next-diplomatic-us-iran-meeting-be-in-another-country-by-september-30-2026-20260622185050781",
   "yes_price": 0.0085,
   "volume_24h": 520585.67533199996,
   "volume": 544013.9037479998,
   "end_date": "2026-09-30T23:59:00Z",
   "lat": 32.4279,
   "lng": 53.688,
   "region": "Iran",
   "category": ""
  },
  {
   "id": "2721764",
   "question": "Mexico vs. Ecuador: Team to Advance",
   "slug": "fifwc-mex-ecu-2026-06-30-team-to-advance",
   "url": "https://polymarket.com/event/fifwc-mex-ecu-2026-06-30-team-to-advance",
   "yes_price": 0.635,
   "volume_24h": 517105.24883500213,
   "volume": 636906.7069880092,
   "end_date": "2026-07-01T01:00:00Z",
   "lat": 23.6345,
   "lng": -102.5528,
   "region": "Mexico",
   "category": ""
  },
  {
   "id": "693485",
   "question": "Will Lebanon recognize Israel by June 30?",
   "slug": "will-lebanon-recognize-israel-by-june-30",
   "url": "https://polymarket.com/event/will-lebanon-recognize-israel-by-june-30",
   "yes_price": 0.1995,
   "volume_24h": 480347.5940220001,
   "volume": 1185210.128640999,
   "end_date": null,
   "lat": 31.0461,
   "lng": 34.8516,
   "region": "Israel",
   "category": ""
  },
  {
   "id": "682709",
   "question": "Will Benny Gantz be the next Prime Minister of Israel?",
   "slug": "will-benny-gantz-be-the-next-prime-minister-of-israel",
   "url": "https://polymarket.com/event/will-benny-gantz-be-the-next-prime-minister-of-israel",
   "yes_price": 0.0045,
   "volume_24h": 405297.50824500003,
   "volume": 1792859.8916970002,
   "end_date": "2026-12-31T00:00:00Z",
   "lat": 31.0461,
   "lng": 34.8516,
   "region": "Israel",
   "category": ""
  },
  {
   "id": "2643404",
   "question": "Will the US announce a blockade on Iran by June 30?",
   "slug": "will-the-us-announce-a-blockade-on-iran-by-june-30-20260622191116911",
   "url": "https://polymarket.com/event/will-the-us-announce-a-blockade-on-iran-by-june-30-20260622191116911",
   "yes_price": 0.004,
   "volume_24h": 366986.532721,
   "volume": 497466.794144,
   "end_date": "2026-06-30T23:59:00Z",
   "lat": 32.4279,
   "lng": 53.688,
   "region": "Iran",
   "category": ""
  },
  {
   "id": "2719431",
   "question": "Spread: Mexico (-1.5)",
   "slug": "fifwc-mex-ecu-2026-06-30-spread-home-1pt5",
   "url": "https://polymarket.com/event/fifwc-mex-ecu-2026-06-30-spread-home-1pt5",
   "yes_price": 0.195,
   "volume_24h": 301762.481189,
   "volume": 342808.2469819997,
   "end_date": "2026-07-01T01:00:00Z",
   "lat": 23.6345,
   "lng": -102.5528,
   "region": "Mexico",
   "category": ""
  },
  {
   "id": "1654957",
   "question": "Will the Fed decrease interest rates by 25 bps after the July 2026 meeting?",
   "slug": "will-the-fed-decrease-interest-rates-by-25-bps-after-the-july-2026-meeting",
   "url": "https://polymarket.com/event/will-the-fed-decrease-interest-rates-by-25-bps-after-the-july-2026-meeting",
   "yes_price": 0.0115,
   "volume_24h": 259790.61172400025,
   "volume": 4673506.111112115,
   "end_date": "2026-07-29T00:00:00Z",
   "lat": 38.9072,
   "lng": -77.0369,
   "region": "Federal Reserve",
   "category": ""
  },
  {
   "id": "2718956",
   "question": "Exact Score: Mexico 3 - 3 Ecuador?",
   "slug": "fifwc-mex-ecu-2026-06-30-exact-score-3-3",
   "url": "https://polymarket.com/event/fifwc-mex-ecu-2026-06-30-exact-score-3-3",
   "yes_price": 0.0055,
   "volume_24h": 257042.94797600005,
   "volume": 273417.63563599985,
   "end_date": "2026-07-01T01:00:00Z",
   "lat": 23.6345,
   "lng": -102.5528,
   "region": "Mexico",
   "category": ""
  },
  {
   "id": "1654958",
   "question": "Will there be no change in Fed interest rates after the July 2026 meeting?",
   "slug": "will-there-be-no-change-in-fed-interest-rates-after-the-july-2026-meeting",
   "url": "https://polymarket.com/event/will-there-be-no-change-in-fed-interest-rates-after-the-july-2026-meeting",
   "yes_price": 0.795,
   "volume_24h": 255794.07100900004,
   "volume": 5402202.90538602,
   "end_date": "2026-07-29T00:00:00Z",
   "lat": 38.9072,
   "lng": -77.0369,
   "region": "Federal Reserve",
   "category": ""
  },
  {
   "id": "2643399",
   "question": "Will Iran announce withdrawal from MOU negotiations by June 30?",
   "slug": "will-iran-announce-withdrawal-from-mou-negotiations-by-june-30-20260622191733845",
   "url": "https://polymarket.com/event/will-iran-announce-withdrawal-from-mou-negotiations-by-june-30-20260622191733845",
   "yes_price": 0.002,
   "volume_24h": 245410.783871,
   "volume": 514408.2897489999,
   "end_date": "2026-06-30T23:59:00Z",
   "lat": 32.4279,
   "lng": 53.688,
   "region": "Iran",
   "category": ""
  },
  {
   "id": "2535468",
   "question": "Strait of Hormuz traffic returns to normal by July 15?",
   "slug": "strait-of-hormuz-traffic-returns-to-normal-by-july-15",
   "url": "https://polymarket.com/event/strait-of-hormuz-traffic-returns-to-normal-by-july-15",
   "yes_price": 0.145,
   "volume_24h": 218048.06852499992,
   "volume": 5316452.162719955,
   "end_date": "2026-07-15T00:00:00Z",
   "lat": 26.5667,
   "lng": 56.25,
   "region": "Strait of Hormuz",
   "category": ""
  },
  {
   "id": "2718893",
   "question": "Will Mexico vs. Ecuador end in a draw?",
   "slug": "fifwc-mex-ecu-2026-06-30-draw",
   "url": "https://polymarket.com/event/fifwc-mex-ecu-2026-06-30-draw",
   "yes_price": 0.335,
   "volume_24h": 209525.52899100122,
   "volume": 530370.7113499865,
   "end_date": "2026-07-01T01:00:00Z",
   "lat": 23.6345,
   "lng": -102.5528,
   "region": "Mexico",
   "category": ""
  },
  {
   "id": "947289",
   "question": "Will Roberto Sánchez Palomino win the 2026 Peruvian presidential election?",
   "slug": "will-roberto-snchez-palomino-win-the-2026-peruvian-presidential-election",
   "url": "https://polymarket.com/event/will-roberto-snchez-palomino-win-the-2026-peruvian-presidential-election",
   "yes_price": 0.0005,
   "volume_24h": 204528.83456600003,
   "volume": 36445534.1539358,
   "end_date": "2026-06-07T00:00:00Z",
   "lat": 38.9072,
   "lng": -77.0369,
   "region": "US Election",
   "category": ""
  },
  {
   "id": "561231",
   "question": "Will Alexandria Ocasio-Cortez win the 2028 US Presidential Election?",
   "slug": "will-alexandria-ocasio-cortez-win-the-2028-us-presidential-election",
   "url": "https://polymarket.com/event/will-alexandria-ocasio-cortez-win-the-2028-us-presidential-election",
   "yes_price": 0.0495,
   "volume_24h": 197523.99345199997,
   "volume": 12382704.521249881,
   "end_date": "2028-11-07T00:00:00Z",
   "lat": 38.9072,
   "lng": -77.0369,
   "region": "US Election",
   "category": ""
  },
  {
   "id": "1708086",
   "question": "Kharg Island no longer under Iranian control by June 30?",
   "slug": "kharg-island-no-longer-under-iranian-control-by-june-30-561-854-897",
   "url": "https://polymarket.com/event/kharg-island-no-longer-under-iranian-control-by-june-30-561-854-897",
   "yes_price": 0.0005,
   "volume_24h": 196320.561,
   "volume": 13456208.233449103,
   "end_date": "2026-06-30T23:55:00Z",
   "lat": 32.4279,
   "lng": 53.688,
   "region": "Iran",
   "category": ""
  },
  {
   "id": "2646915",
   "question": "Will the next diplomatic US-Iran meeting be in Oman by September 30, 2026?",
   "slug": "will-the-next-diplomatic-us-iran-meeting-be-in-oman-by-september-30-2026-20260622185050764",
   "url": "https://polymarket.com/event/will-the-next-diplomatic-us-iran-meeting-be-in-oman-by-september-30-2026-20260622185050764",
   "yes_price": 0.0095,
   "volume_24h": 190724.65888599996,
   "volume": 217388.34670199992,
   "end_date": "2026-09-30T23:59:00Z",
   "lat": 32.4279,
   "lng": 53.688,
   "region": "Iran",
   "category": ""
  },
  {
   "id": "2410576",
   "question": "Will Bitcoin dip to $55,000 in June?",
   "slug": "will-bitcoin-dip-to-55k-in-june-2026-779-111",
   "url": "https://polymarket.com/event/will-bitcoin-dip-to-55k-in-june-2026-779-111",
   "yes_price": 0.014,
   "volume_24h": 187877.6274780001,
   "volume": 3587819.992219994,
   "end_date": "2026-07-01T04:00:00Z",
   "lat": 37.7749,
   "lng": -122.4194,
   "region": "Bitcoin (SF proxy)",
   "category": ""
  },
  {
   "id": "2646848",
   "question": "US x Iran diplomatic meeting by July 3, 2026?",
   "slug": "us-x-iran-diplomatic-meeting-by-july-3-2026-20260622191708359",
   "url": "https://polymarket.com/event/us-x-iran-diplomatic-meeting-by-july-3-2026-20260622191708359",
   "yes_price": 0.185,
   "volume_24h": 187209.72914000004,
   "volume": 1067368.9125709995,
   "end_date": "2026-07-03T23:59:00Z",
   "lat": 32.4279,
   "lng": 53.688,
   "region": "Iran",
   "category": ""
  }
 ]
}