{
 "generated_at": "2026-06-10T04:38:41+00:00",
 "count": 48,
 "markets": [
  {
   "id": "947289",
   "question": "Will Roberto Sánchez Palomino win the 2026 Peruvian presidential election?",
   "slug": "will-roberto-snchez-palomino-win-the-2026-peruvian-presidential-election",
   "url": "https://polymarket.com/event/will-roberto-snchez-palomino-win-the-2026-peruvian-presidential-election",
   "yes_price": 0.0695,
   "volume_24h": 3526109.4401740134,
   "volume": 26691757.312734663,
   "end_date": "2026-06-07T00:00:00Z",
   "lat": 38.9072,
   "lng": -77.0369,
   "region": "US Election",
   "category": ""
  },
  {
   "id": "2270330",
   "question": "US x Iran permanent peace deal by June 15, 2026?",
   "slug": "us-x-iran-permanent-peace-deal-by-june-15-2026-734-856-129",
   "url": "https://polymarket.com/event/us-x-iran-permanent-peace-deal-by-june-15-2026-734-856-129",
   "yes_price": 0.045,
   "volume_24h": 3079732.803207998,
   "volume": 20872455.625270754,
   "end_date": "2026-06-15T00:00:00Z",
   "lat": 32.4279,
   "lng": 53.688,
   "region": "Iran",
   "category": ""
  },
  {
   "id": "558961",
   "question": "Will South Korea win the 2026 FIFA World Cup?",
   "slug": "will-south-korea-win-the-2026-fifa-world-cup-485",
   "url": "https://polymarket.com/event/will-south-korea-win-the-2026-fifa-world-cup-485",
   "yes_price": 0.0025,
   "volume_24h": 2607944.632633,
   "volume": 45100877.30543073,
   "end_date": "2026-07-20T00:00:00Z",
   "lat": 35.9078,
   "lng": 127.7669,
   "region": "South Korea",
   "category": ""
  },
  {
   "id": "558945",
   "question": "Will Mexico win the 2026 FIFA World Cup?",
   "slug": "will-mexico-win-the-2026-fifa-world-cup-529",
   "url": "https://polymarket.com/event/will-mexico-win-the-2026-fifa-world-cup-529",
   "yes_price": 0.0135,
   "volume_24h": 2287787.5545940027,
   "volume": 41647294.32101844,
   "end_date": "2026-07-20T00:00:00Z",
   "lat": 23.6345,
   "lng": -102.5528,
   "region": "Mexico",
   "category": ""
  },
  {
   "id": "558938",
   "question": "Will Argentina win the 2026 FIFA World Cup?",
   "slug": "will-argentina-win-the-2026-fifa-world-cup-245",
   "url": "https://polymarket.com/event/will-argentina-win-the-2026-fifa-world-cup-245",
   "yes_price": 0.0855,
   "volume_24h": 2234172.658639008,
   "volume": 31776960.237294115,
   "end_date": "2026-07-20T00:00:00Z",
   "lat": -38.4161,
   "lng": -63.6167,
   "region": "Argentina",
   "category": ""
  },
  {
   "id": "558949",
   "question": "Will Japan win the 2026 FIFA World Cup?",
   "slug": "will-japan-win-the-2026-fifa-world-cup-112",
   "url": "https://polymarket.com/event/will-japan-win-the-2026-fifa-world-cup-112",
   "yes_price": 0.0175,
   "volume_24h": 1737899.1378869982,
   "volume": 37830853.3113623,
   "end_date": "2026-07-20T00:00:00Z",
   "lat": 36.2048,
   "lng": 138.2529,
   "region": "Japan",
   "category": ""
  },
  {
   "id": "947271",
   "question": "Will Carlos Álvarez win the 2026 Peruvian presidential election?",
   "slug": "will-carlos-lvarez-win-the-2026-peruvian-presidential-election",
   "url": "https://polymarket.com/event/will-carlos-lvarez-win-the-2026-peruvian-presidential-election",
   "yes_price": 0.0005,
   "volume_24h": 1653430.8399999999,
   "volume": 13157623.756722001,
   "end_date": "2026-04-12T00:00:00Z",
   "lat": 38.9072,
   "lng": -77.0369,
   "region": "US Election",
   "category": ""
  },
  {
   "id": "558959",
   "question": "Will Iran win the 2026 FIFA World Cup?",
   "slug": "will-iran-win-the-2026-fifa-world-cup-788",
   "url": "https://polymarket.com/event/will-iran-win-the-2026-fifa-world-cup-788",
   "yes_price": 0.0015,
   "volume_24h": 1626481.0959999992,
   "volume": 41774407.64379001,
   "end_date": "2026-07-20T00:00:00Z",
   "lat": 32.4279,
   "lng": 53.688,
   "region": "Iran",
   "category": ""
  },
  {
   "id": "558937",
   "question": "Will Brazil win the 2026 FIFA World Cup?",
   "slug": "will-brazil-win-the-2026-fifa-world-cup-183",
   "url": "https://polymarket.com/event/will-brazil-win-the-2026-fifa-world-cup-183",
   "yes_price": 0.0845,
   "volume_24h": 1581344.4761609992,
   "volume": 31572803.818486117,
   "end_date": "2026-07-20T00:00:00Z",
   "lat": -14.235,
   "lng": -51.9253,
   "region": "Brazil",
   "category": ""
  },
  {
   "id": "947269",
   "question": "Will Keiko Fujimori win the 2026 Peruvian presidential election?",
   "slug": "will-keiko-fujimori-win-the-2026-peruvian-presidential-election",
   "url": "https://polymarket.com/event/will-keiko-fujimori-win-the-2026-peruvian-presidential-election",
   "yes_price": 0.935,
   "volume_24h": 1496507.137854,
   "volume": 17869885.516893156,
   "end_date": "2026-06-07T00:00:00Z",
   "lat": 38.9072,
   "lng": -77.0369,
   "region": "US Election",
   "category": ""
  },
  {
   "id": "2420753",
   "question": "US announces new Iran agreement/ceasefire extension by June 9?",
   "slug": "us-announces-new-iran-agreementceasefire-extension-by-june-9",
   "url": "https://polymarket.com/event/us-announces-new-iran-agreementceasefire-extension-by-june-9",
   "yes_price": 0.0015,
   "volume_24h": 1440598.8041310003,
   "volume": 2287997.3817909984,
   "end_date": "2026-06-30T00:00:00Z",
   "lat": 32.4279,
   "lng": 53.688,
   "region": "Iran",
   "category": ""
  },
  {
   "id": "558964",
   "question": "Will South Africa win the 2026 FIFA World Cup?",
   "slug": "will-south-africa-win-the-2026-fifa-world-cup",
   "url": "https://polymarket.com/event/will-south-africa-win-the-2026-fifa-world-cup",
   "yes_price": 0.0005,
   "volume_24h": 1114243.9500000002,
   "volume": 37659430.207894266,
   "end_date": "2026-07-20T00:00:00Z",
   "lat": -30.5595,
   "lng": 22.9375,
   "region": "South Africa",
   "category": ""
  },
  {
   "id": "1962237",
   "question": "US x Iran permanent peace deal by June 30, 2026?",
   "slug": "us-x-iran-permanent-peace-deal-by-june-30-2026-837-641-896-877-363-892-537-597",
   "url": "https://polymarket.com/event/us-x-iran-permanent-peace-deal-by-june-30-2026-837-641-896-877-363-892-537-597",
   "yes_price": 0.155,
   "volume_24h": 870876.1408330005,
   "volume": 21655562.433640588,
   "end_date": "2026-05-31T00:00:00Z",
   "lat": 32.4279,
   "lng": 53.688,
   "region": "Iran",
   "category": ""
  },
  {
   "id": "906976",
   "question": "Will the Fed increase interest rates by 50+ bps after the June 2026 meeting?",
   "slug": "will-the-fed-increase-interest-rates-by-50-bps-after-the-june-2026-meeting",
   "url": "https://polymarket.com/event/will-the-fed-increase-interest-rates-by-50-bps-after-the-june-2026-meeting",
   "yes_price": 0.0005,
   "volume_24h": 798061.46,
   "volume": 18041535.24439868,
   "end_date": "2026-06-17T00:00:00Z",
   "lat": 38.9072,
   "lng": -77.0369,
   "region": "Federal Reserve",
   "category": ""
  },
  {
   "id": "2466412",
   "question": "Israel closes its airspace by June 9?",
   "slug": "israel-closes-its-airspace-by-june-9",
   "url": "https://polymarket.com/event/israel-closes-its-airspace-by-june-9",
   "yes_price": 0.001,
   "volume_24h": 738727.1430510002,
   "volume": 1204796.8616310002,
   "end_date": "2026-06-09T00:00:00Z",
   "lat": 31.0461,
   "lng": 34.8516,
   "region": "Israel",
   "category": ""
  },
  {
   "id": "906975",
   "question": "Will the Fed increase interest rates by 25 bps after the June 2026 meeting?",
   "slug": "will-the-fed-increase-interest-rates-by-25-bps-after-the-june-2026-meeting",
   "url": "https://polymarket.com/event/will-the-fed-increase-interest-rates-by-25-bps-after-the-june-2026-meeting",
   "yes_price": 0.007,
   "volume_24h": 698597.6790030003,
   "volume": 12881448.652650086,
   "end_date": "2026-06-17T00:00:00Z",
   "lat": 38.9072,
   "lng": -77.0369,
   "region": "Federal Reserve",
   "category": ""
  },
  {
   "id": "2429034",
   "question": "Iran closes its airspace by June 8?",
   "slug": "iran-closes-its-airspace-by-june-8",
   "url": "https://polymarket.com/event/iran-closes-its-airspace-by-june-8",
   "yes_price": 0.9995,
   "volume_24h": 567542.09,
   "volume": 10835567.573117051,
   "end_date": "2026-06-08T00:00:00Z",
   "lat": 32.4279,
   "lng": 53.688,
   "region": "Iran",
   "category": ""
  },
  {
   "id": "906974",
   "question": "Will there be no change in Fed interest rates after the June 2026 meeting?",
   "slug": "will-there-be-no-change-in-fed-interest-rates-after-the-june-2026-meeting",
   "url": "https://polymarket.com/event/will-there-be-no-change-in-fed-interest-rates-after-the-june-2026-meeting",
   "yes_price": 0.9905,
   "volume_24h": 518973.8889299998,
   "volume": 13660696.887012891,
   "end_date": "2026-06-17T00:00:00Z",
   "lat": 38.9072,
   "lng": -77.0369,
   "region": "Federal Reserve",
   "category": ""
  },
  {
   "id": "906972",
   "question": "Will the Fed decrease interest rates by 50+ bps after the June 2026 meeting?",
   "slug": "will-the-fed-decrease-interest-rates-by-50-bps-after-the-june-2026-meeting",
   "url": "https://polymarket.com/event/will-the-fed-decrease-interest-rates-by-50-bps-after-the-june-2026-meeting",
   "yes_price": 0.0015,
   "volume_24h": 507242.9950000005,
   "volume": 17804598.884853277,
   "end_date": "2026-06-17T00:00:00Z",
   "lat": 38.9072,
   "lng": -77.0369,
   "region": "Federal Reserve",
   "category": ""
  },
  {
   "id": "958443",
   "question": "Will the Iranian regime fall by June 30?",
   "slug": "will-the-iranian-regime-fall-by-june-30",
   "url": "https://polymarket.com/event/will-the-iranian-regime-fall-by-june-30",
   "yes_price": 0.0145,
   "volume_24h": 485613.2843969997,
   "volume": 51026328.08394331,
   "end_date": "2026-06-30T00:00:00Z",
   "lat": 32.4279,
   "lng": 53.688,
   "region": "Iran",
   "category": ""
  },
  {
   "id": "1971905",
   "question": "Strait of Hormuz traffic returns to normal by end of June?",
   "slug": "strait-of-hormuz-traffic-returns-to-normal-by-end-of-june",
   "url": "https://polymarket.com/event/strait-of-hormuz-traffic-returns-to-normal-by-end-of-june",
   "yes_price": 0.095,
   "volume_24h": 472765.7227670001,
   "volume": 16001050.53001424,
   "end_date": "2026-06-30T00:00:00Z",
   "lat": 26.5667,
   "lng": 56.25,
   "region": "Strait of Hormuz",
   "category": ""
  },
  {
   "id": "906973",
   "question": "Will the Fed decrease interest rates by 25 bps after the June 2026 meeting?",
   "slug": "will-the-fed-decrease-interest-rates-by-25-bps-after-the-june-2026-meeting",
   "url": "https://polymarket.com/event/will-the-fed-decrease-interest-rates-by-25-bps-after-the-june-2026-meeting",
   "yes_price": 0.0035,
   "volume_24h": 469678.103497,
   "volume": 13747664.451501012,
   "end_date": "2026-06-17T00:00:00Z",
   "lat": 38.9072,
   "lng": -77.0369,
   "region": "Federal Reserve",
   "category": ""
  },
  {
   "id": "1708086",
   "question": "Kharg Island no longer under Iranian control by June 30?",
   "slug": "kharg-island-no-longer-under-iranian-control-by-june-30-561-854",
   "url": "https://polymarket.com/event/kharg-island-no-longer-under-iranian-control-by-june-30-561-854",
   "yes_price": 0.0305,
   "volume_24h": 440112.7647959999,
   "volume": 7367102.531338251,
   "end_date": "2026-06-30T23:55:00Z",
   "lat": 32.4279,
   "lng": 53.688,
   "region": "Iran",
   "category": ""
  },
  {
   "id": "2296152",
   "question": "Israel closes its airspace by June 15?",
   "slug": "israel-closes-its-airspace-by-june-15-687-594-783-732-455-613-653",
   "url": "https://polymarket.com/event/israel-closes-its-airspace-by-june-15-687-594-783-732-455-613-653",
   "yes_price": 0.145,
   "volume_24h": 400432.1830810001,
   "volume": 4156038.410451961,
   "end_date": "2026-06-15T00:00:00Z",
   "lat": 31.0461,
   "lng": 34.8516,
   "region": "Israel",
   "category": ""
  },
  {
   "id": "2296150",
   "question": "Iran closes its airspace by June 15?",
   "slug": "iran-closes-its-airspace-by-june-15-219",
   "url": "https://polymarket.com/event/iran-closes-its-airspace-by-june-15-219",
   "yes_price": 0.9995,
   "volume_24h": 369282.46,
   "volume": 4375564.456406001,
   "end_date": "2026-06-15T00:00:00Z",
   "lat": 32.4279,
   "lng": 53.688,
   "region": "Iran",
   "category": ""
  },
  {
   "id": "957019",
   "question": "US-Iran nuclear deal by June 30?",
   "slug": "us-iran-nuclear-deal-by-june-30",
   "url": "https://polymarket.com/event/us-iran-nuclear-deal-by-june-30",
   "yes_price": 0.185,
   "volume_24h": 334020.61395100004,
   "volume": 6475944.331334084,
   "end_date": "2026-06-30T00:00:00Z",
   "lat": 32.4279,
   "lng": 53.688,
   "region": "Iran",
   "category": ""
  },
  {
   "id": "2475211",
   "question": "Trump announces US x Iran ceasefire over by June 12?",
   "slug": "trump-announces-us-x-iran-ceasefire-over-by-june-12-20260607232556274",
   "url": "https://polymarket.com/event/trump-announces-us-x-iran-ceasefire-over-by-june-12-20260607232556274",
   "yes_price": 0.057,
   "volume_24h": 313868.01889100036,
   "volume": 318659.245339,
   "end_date": "2026-06-13T03:59:00Z",
   "lat": 32.4279,
   "lng": 53.688,
   "region": "Iran",
   "category": ""
  },
  {
   "id": "948956",
   "question": "Bitcoin all time high by June 30, 2026?",
   "slug": "bitcoin-all-time-high-by-june-30-2026",
   "url": "https://polymarket.com/event/bitcoin-all-time-high-by-june-30-2026",
   "yes_price": 0.0005,
   "volume_24h": 297553.00501499994,
   "volume": 2542508.282626898,
   "end_date": "2026-07-01T05:00:00Z",
   "lat": 37.7749,
   "lng": -122.4194,
   "region": "Bitcoin (SF proxy)",
   "category": ""
  },
  {
   "id": "2354003",
   "question": "US announces new Iran agreement/ceasefire extension by June 30?",
   "slug": "us-announces-new-iran-agreementceasefire-extension-by-june-30-848-925-757-129-337",
   "url": "https://polymarket.com/event/us-announces-new-iran-agreementceasefire-extension-by-june-30-848-925-757-129-337",
   "yes_price": 0.42,
   "volume_24h": 293361.9220060001,
   "volume": 1874136.9014590026,
   "end_date": "2026-06-30T00:00:00Z",
   "lat": 32.4279,
   "lng": 53.688,
   "region": "Iran",
   "category": ""
  },
  {
   "id": "947268",
   "question": "Will Rafael López Aliaga win the 2026 Peruvian presidential election?",
   "slug": "will-rafael-lpez-aliaga-win-the-2026-peruvian-presidential-election",
   "url": "https://polymarket.com/event/will-rafael-lpez-aliaga-win-the-2026-peruvian-presidential-election",
   "yes_price": 0.0015,
   "volume_24h": 293171.632332,
   "volume": 13706223.390168743,
   "end_date": "2026-06-07T00:00:00Z",
   "lat": 38.9072,
   "lng": -77.0369,
   "region": "US Election",
   "category": ""
  },
  {
   "id": "2354976",
   "question": "Strait of Hormuz traffic returns to normal by June 15?",
   "slug": "strait-of-hormuz-traffic-returns-to-normal-by-june-15",
   "url": "https://polymarket.com/event/strait-of-hormuz-traffic-returns-to-normal-by-june-15",
   "yes_price": 0.0095,
   "volume_24h": 287914.045262,
   "volume": 5181975.4539540345,
   "end_date": "2026-06-15T00:00:00Z",
   "lat": 26.5667,
   "lng": 56.25,
   "region": "Strait of Hormuz",
   "category": ""
  },
  {
   "id": "2420771",
   "question": "US announces new Iran agreement/ceasefire extension by June 12?",
   "slug": "us-announces-new-iran-agreementceasefire-extension-by-june-12-2482",
   "url": "https://polymarket.com/event/us-announces-new-iran-agreementceasefire-extension-by-june-12-2482",
   "yes_price": 0.085,
   "volume_24h": 272920.77198400005,
   "volume": 862535.3226889966,
   "end_date": "2026-05-29T00:00:00Z",
   "lat": 32.4279,
   "lng": 53.688,
   "region": "Iran",
   "category": ""
  },
  {
   "id": "2262267",
   "question": "Will Rebecca Shepherd win the 2026 Makerfield by-election?",
   "slug": "will-rebecca-shepherd-win-the-2026-makerfield-by-election",
   "url": "https://polymarket.com/event/will-rebecca-shepherd-win-the-2026-makerfield-by-election",
   "yes_price": 0.0255,
   "volume_24h": 254557.2712419998,
   "volume": 2465107.3247359945,
   "end_date": null,
   "lat": 38.9072,
   "lng": -77.0369,
   "region": "US Election",
   "category": ""
  },
  {
   "id": "2002564",
   "question": "Israel x Iran permanent peace deal by June 30, 2026?",
   "slug": "israel-x-iran-permanent-peace-deal-by-june-30-2026-262",
   "url": "https://polymarket.com/event/israel-x-iran-permanent-peace-deal-by-june-30-2026-262",
   "yes_price": 0.0415,
   "volume_24h": 254439.94999900003,
   "volume": 2911240.2836940233,
   "end_date": "2026-06-30T00:00:00Z",
   "lat": 32.4279,
   "lng": 53.688,
   "region": "Iran",
   "category": ""
  },
  {
   "id": "628937",
   "question": "Will Alex Padilla win the California Governor Election in 2026?",
   "slug": "will-alex-padilla-win-the-california-governor-election-in-2026",
   "url": "https://polymarket.com/event/will-alex-padilla-win-the-california-governor-election-in-2026",
   "yes_price": 0.0005,
   "volume_24h": 249662.307,
   "volume": 1588951.7404449952,
   "end_date": "2026-11-03T00:00:00Z",
   "lat": 38.9072,
   "lng": -77.0369,
   "region": "US Election",
   "category": ""
  },
  {
   "id": "665374",
   "question": "Will the U.S. invade Iran before 2027?",
   "slug": "will-the-us-invade-iran-before-2027",
   "url": "https://polymarket.com/event/will-the-us-invade-iran-before-2027",
   "yes_price": 0.175,
   "volume_24h": 243490.669386,
   "volume": 34970907.75409791,
   "end_date": "2026-12-31T00:00:00Z",
   "lat": 32.4279,
   "lng": 53.688,
   "region": "Iran",
   "category": ""
  },
  {
   "id": "2155052",
   "question": "US x Iran permanent peace deal by December 31, 2026?",
   "slug": "us-x-iran-permanent-peace-deal-by-december-31-2026-961-587-341-574-555-817",
   "url": "https://polymarket.com/event/us-x-iran-permanent-peace-deal-by-december-31-2026-961-587-341-574-555-817",
   "yes_price": 0.675,
   "volume_24h": 225699.86411899995,
   "volume": 9241665.483424034,
   "end_date": "2026-12-31T00:00:00Z",
   "lat": 32.4279,
   "lng": 53.688,
   "region": "Iran",
   "category": ""
  },
  {
   "id": "629035",
   "question": "Will Spencer Pratt win the 2026 Los Angeles mayoral election?",
   "slug": "will-spencer-pratt-win-the-2026-los-angeles-mayoral-election-983",
   "url": "https://polymarket.com/event/will-spencer-pratt-win-the-2026-los-angeles-mayoral-election-983",
   "yes_price": 0.007,
   "volume_24h": 225395.94333200002,
   "volume": 6241319.465758032,
   "end_date": "2026-06-02T00:00:00Z",
   "lat": 38.9072,
   "lng": -77.0369,
   "region": "US Election",
   "category": ""
  },
  {
   "id": "2428523",
   "question": "Will the price of Bitcoin be above $56,000 on June 10?",
   "slug": "bitcoin-above-56k-on-june-10-2026",
   "url": "https://polymarket.com/event/bitcoin-above-56k-on-june-10-2026",
   "yes_price": 0.9985,
   "volume_24h": 224899.18799200052,
   "volume": 296969.3545850004,
   "end_date": "2026-06-10T16:00:00Z",
   "lat": 37.7749,
   "lng": -122.4194,
   "region": "Bitcoin (SF proxy)",
   "category": ""
  },
  {
   "id": "628949",
   "question": "Will Daniel Mercuri win the California Governor Election in 2026?",
   "slug": "will-daniel-mercuri-win-the-california-governor-election-in-2026",
   "url": "https://polymarket.com/event/will-daniel-mercuri-win-the-california-governor-election-in-2026",
   "yes_price": 0.0005,
   "volume_24h": 218951.924,
   "volume": 1384140.3379339937,
   "end_date": "2026-11-03T00:00:00Z",
   "lat": 38.9072,
   "lng": -77.0369,
   "region": "US Election",
   "category": ""
  },
  {
   "id": "2176262",
   "question": "Strait of Hormuz traffic returns to normal by July 31?",
   "slug": "strait-of-hormuz-traffic-returns-to-normal-by-july-31",
   "url": "https://polymarket.com/event/strait-of-hormuz-traffic-returns-to-normal-by-july-31",
   "yes_price": 0.3,
   "volume_24h": 215576.61546000003,
   "volume": 3406655.673062957,
   "end_date": "2026-07-31T00:00:00Z",
   "lat": 26.5667,
   "lng": 56.25,
   "region": "Strait of Hormuz",
   "category": ""
  },
  {
   "id": "2466413",
   "question": "Israel closes its airspace by June 10?",
   "slug": "israel-closes-its-airspace-by-june-10",
   "url": "https://polymarket.com/event/israel-closes-its-airspace-by-june-10",
   "yes_price": 0.0555,
   "volume_24h": 210467.8840549999,
   "volume": 211541.8260650001,
   "end_date": "2026-06-10T00:00:00Z",
   "lat": 31.0461,
   "lng": 34.8516,
   "region": "Israel",
   "category": ""
  },
  {
   "id": "2270338",
   "question": "US x Iran permanent peace deal by July 31, 2026?",
   "slug": "us-x-iran-permanent-peace-deal-by-july-31-2026-831-252",
   "url": "https://polymarket.com/event/us-x-iran-permanent-peace-deal-by-july-31-2026-831-252",
   "yes_price": 0.315,
   "volume_24h": 193520.05206600003,
   "volume": 5677109.815415091,
   "end_date": "2026-07-31T00:00:00Z",
   "lat": 32.4279,
   "lng": 53.688,
   "region": "Iran",
   "category": ""
  },
  {
   "id": "2428541",
   "question": "Will the price of Bitcoin be above $66,000 on June 10?",
   "slug": "bitcoin-above-66k-on-june-10-2026",
   "url": "https://polymarket.com/event/bitcoin-above-66k-on-june-10-2026",
   "yes_price": 0.0015,
   "volume_24h": 192835.22637199998,
   "volume": 226434.2323180001,
   "end_date": "2026-06-10T16:00:00Z",
   "lat": 37.7749,
   "lng": -122.4194,
   "region": "Bitcoin (SF proxy)",
   "category": ""
  },
  {
   "id": "1897034",
   "question": "Will Mexico win on 2026-06-11?",
   "slug": "fifwc-mex-rsa-2026-06-11-mex",
   "url": "https://polymarket.com/event/fifwc-mex-rsa-2026-06-11-mex",
   "yes_price": 0.695,
   "volume_24h": 192770.58799299927,
   "volume": 559180.0308879981,
   "end_date": "2026-06-11T19:00:00Z",
   "lat": 23.6345,
   "lng": -102.5528,
   "region": "Mexico",
   "category": ""
  },
  {
   "id": "2241742",
   "question": "Iran closes its airspace by June 30?",
   "slug": "iran-closes-its-airspace-by-june-30-432-786-462-866-468",
   "url": "https://polymarket.com/event/iran-closes-its-airspace-by-june-30-432-786-462-866-468",
   "yes_price": 0.9995,
   "volume_24h": 187499.33,
   "volume": 5683519.668141011,
   "end_date": "2026-06-30T00:00:00Z",
   "lat": 32.4279,
   "lng": 53.688,
   "region": "Iran",
   "category": ""
  },
  {
   "id": "558972",
   "question": "Will Saudi Arabia win the 2026 FIFA World Cup?",
   "slug": "will-saudi-arabia-win-the-2026-fifa-world-cup",
   "url": "https://polymarket.com/event/will-saudi-arabia-win-the-2026-fifa-world-cup",
   "yes_price": 0.0005,
   "volume_24h": 185248.17,
   "volume": 46033588.432883725,
   "end_date": "2026-07-20T00:00:00Z",
   "lat": 23.8859,
   "lng": 45.0792,
   "region": "Saudi Arabia",
   "category": ""
  },
  {
   "id": "2354024",
   "question": "Will Donald Trump announce that the United States blockade of the Strait of Hormuz has been lifted by June 15, 2026?",
   "slug": "will-donald-trump-announce-that-the-united-states-blockade-of-the-strait-of-hormuz-has-been-lifted-by-june-15-2026",
   "url": "https://polymarket.com/event/will-donald-trump-announce-that-the-united-states-blockade-of-the-strait-of-hormuz-has-been-lifted-by-june-15-2026",
   "yes_price": 0.105,
   "volume_24h": 178454.04380699986,
   "volume": 966434.5947350004,
   "end_date": "2026-06-15T00:00:00Z",
   "lat": 26.5667,
   "lng": 56.25,
   "region": "Strait of Hormuz",
   "category": ""
  }
 ]
}