{
 "markets": [
  {
   "id": "2063134",
   "yes_price": 0.002
  },
  {
   "id": "2063131",
   "yes_price": 0.002
  },
  {
   "id": "558938",
   "yes_price": 0.1315
  },
  {
   "id": "558949",
   "yes_price": 0.0215
  },
  {
   "id": "558961",
   "yes_price": 0.0025
  },
  {
   "id": "569368",
   "yes_price": 0.0085
  },
  {
   "id": "569366",
   "yes_price": 0.9925
  },
  {
   "id": "558937",
   "yes_price": 0.0555
  },
  {
   "id": "558959",
   "yes_price": 0.0005
  },
  {
   "id": "2063135",
   "yes_price": 0.002
  },
  {
   "id": "558945",
   "yes_price": 0.0125
  },
  {
   "id": "1971905",
   "yes_price": 0.065
  },
  {
   "id": "2176262",
   "yes_price": 0.485
  },
  {
   "id": "2099580",
   "yes_price": 0.775
  },
  {
   "id": "1654957",
   "yes_price": 0.0145
  },
  {
   "id": "2535468",
   "yes_price": 0.315
  },
  {
   "id": "1654958",
   "yes_price": 0.725
  },
  {
   "id": "1654959",
   "yes_price": 0.2455
  },
  {
   "id": "947289",
   "yes_price": 0.0045
  },
  {
   "id": "1654956",
   "yes_price": 0.0045
  },
  {
   "id": "839969",
   "yes_price": 0.9985
  },
  {
   "id": "1370652",
   "yes_price": 0.0435
  },
  {
   "id": "1897329",
   "yes_price": 0.515
  },
  {
   "id": "682709",
   "yes_price": 0.0035
  },
  {
   "id": "2566460",
   "yes_price": 0.9995
  }
 ]
}