{
 "markets": [
  {
   "id": "947289",
   "yes_price": 0.0655
  },
  {
   "id": "2270330",
   "yes_price": 0.045
  },
  {
   "id": "558961",
   "yes_price": 0.0025
  },
  {
   "id": "558938",
   "yes_price": 0.0855
  },
  {
   "id": "558945",
   "yes_price": 0.0135
  },
  {
   "id": "558937",
   "yes_price": 0.0845
  },
  {
   "id": "947271",
   "yes_price": 0.0005
  },
  {
   "id": "558959",
   "yes_price": 0.0015
  },
  {
   "id": "558949",
   "yes_price": 0.0175
  },
  {
   "id": "947269",
   "yes_price": 0.935
  },
  {
   "id": "1796310",
   "yes_price": 0.0085
  },
  {
   "id": "558964",
   "yes_price": 0.0005
  },
  {
   "id": "2354976",
   "yes_price": 0.0065
  },
  {
   "id": "1962237",
   "yes_price": 0.165
  },
  {
   "id": "906976",
   "yes_price": 0.0005
  },
  {
   "id": "906975",
   "yes_price": 0.0065
  },
  {
   "id": "906972",
   "yes_price": 0.0015
  },
  {
   "id": "2429034",
   "yes_price": 0.9995
  },
  {
   "id": "906974",
   "yes_price": 0.9905
  },
  {
   "id": "948956",
   "yes_price": 0.0015
  },
  {
   "id": "558972",
   "yes_price": 0.0005
  },
  {
   "id": "958443",
   "yes_price": 0.0135
  },
  {
   "id": "1971905",
   "yes_price": 0.085
  },
  {
   "id": "906973",
   "yes_price": 0.0035
  },
  {
   "id": "1708086",
   "yes_price": 0.027
  },
  {
   "id": "2420771",
   "yes_price": 0.05
  },
  {
   "id": "2296152",
   "yes_price": 0.135
  },
  {
   "id": "2296150",
   "yes_price": 0.9995
  },
  {
   "id": "2428523",
   "yes_price": 0.996
  },
  {
   "id": "947268",
   "yes_price": 0.0015
  },
  {
   "id": "2475211",
   "yes_price": 0.046
  },
  {
   "id": "558971",
   "yes_price": 0.0005
  },
  {
   "id": "2262267",
   "yes_price": 0.0255
  },
  {
   "id": "957019",
   "yes_price": 0.195
  },
  {
   "id": "2354003",
   "yes_price": 0.435
  },
  {
   "id": "2428541",
   "yes_price": 0.0015
  },
  {
   "id": "628937",
   "yes_price": 0.0005
  },
  {
   "id": "665374",
   "yes_price": 0.175
  },
  {
   "id": "2466413",
   "yes_price": 0.0175
  },
  {
   "id": "628949",
   "yes_price": 0.0005
  },
  {
   "id": "2176262",
   "yes_price": 0.295
  },
  {
   "id": "2420774",
   "yes_price": 0.075
  },
  {
   "id": "2002564",
   "yes_price": 0.043
  },
  {
   "id": "2270338",
   "yes_price": 0.305
  },
  {
   "id": "1897034",
   "yes_price": 0.695
  },
  {
   "id": "2241742",
   "yes_price": 0.9995
  },
  {
   "id": "629035",
   "yes_price": 0.0055
  },
  {
   "id": "2354024",
   "yes_price": 0.105
  },
  {
   "id": "2428526",
   "yes_price": 0.982
  },
  {
   "id": "2155023",
   "yes_price": 0.375
  },
  {
   "id": "2475213",
   "yes_price": 0.095
  },
  {
   "id": "2428537",
   "yes_price": 0.0175
  },
  {
   "id": "2428453",
   "yes_price": 0.0005
  }
 ]
}